{"mc":{
	"stand":{
		"frameRate":24,
		"frames":[
			{"res":"010000","x":-20,"y":-77},
			{"res":"010001","x":-20,"y":-77},
			{"res":"010002","x":-19,"y":-77},
			{"res":"010003","x":-20,"y":-77},
			{"res":"020000","x":-23,"y":-82},
			{"res":"020001","x":-24,"y":-81},
			{"res":"020002","x":-24,"y":-81},
			{"res":"020003","x":-23,"y":-82},
			{"res":"030000","x":-15,"y":-87},
			{"res":"030001","x":-16,"y":-87},
			{"res":"030002","x":-16,"y":-88},
			{"res":"030003","x":-16,"y":-87},
			{"res":"040000","x":-76,"y":-75},
			{"res":"040001","x":-75,"y":-87},
			{"res":"040002","x":-75,"y":-87},
			{"res":"040003","x":-75,"y":-87},
			{"res":"050000","x":-112,"y":-86},
			{"res":"050001","x":-112,"y":-87},
			{"res":"050002","x":-112,"y":-87},
			{"res":"050003","x":-112,"y":-87}

		]
}},
"res":{
	"010000":{"x":0,"y":0,"w":132,"h":99},
	"010001":{"x":132,"y":0,"w":132,"h":98},
	"010002":{"x":264,"y":0,"w":131,"h":97},
	"010003":{"x":395,"y":0,"w":132,"h":98},
	"020000":{"x":527,"y":0,"w":109,"h":127},
	"020001":{"x":636,"y":0,"w":111,"h":125},
	"020002":{"x":747,"y":0,"w":111,"h":125},
	"020003":{"x":858,"y":0,"w":110,"h":126},
	"030000":{"x":968,"y":0,"w":28,"h":145},
	"030001":{"x":996,"y":0,"w":30,"h":145},
	"030002":{"x":1026,"y":0,"w":30,"h":146},
	"030003":{"x":1056,"y":0,"w":30,"h":145},
	"040000":{"x":1086,"y":0,"w":73,"h":121},
	"040001":{"x":1159,"y":0,"w":73,"h":133},
	"040002":{"x":1232,"y":0,"w":73,"h":133},
	"040003":{"x":1305,"y":0,"w":73,"h":133},
	"050000":{"x":1378,"y":0,"w":132,"h":101},
	"050001":{"x":1510,"y":0,"w":132,"h":102},
	"050002":{"x":1642,"y":0,"w":131,"h":103},
	"050003":{"x":1773,"y":0,"w":132,"h":102}

}}