{"mc":{
	"stand":{
		"frameRate":24,
		"frames":[
			{"res":"00000","x":-70,"y":-112},
			{"res":"00001","x":-70,"y":-113},
			{"res":"00002","x":-70,"y":-115},
			{"res":"00003","x":-70,"y":-116},
			{"res":"00004","x":-70,"y":-115},
			{"res":"00005","x":-70,"y":-113}

		]
}},
"res":{
	"00000":{"x":0,"y":0,"w":140,"h":200},
	"00001":{"x":140,"y":0,"w":140,"h":200},
	"00002":{"x":280,"y":0,"w":140,"h":200},
	"00003":{"x":420,"y":0,"w":140,"h":200},
	"00004":{"x":560,"y":0,"w":140,"h":200},
	"00005":{"x":700,"y":0,"w":140,"h":200}

}}