{"mc":{
	"run2":{
		"frameRate":24,
		"frames":[
			{"res":"00032.png","x":-34,"y":-76},
			{"res":"00033.png","x":-33,"y":-79},
			{"res":"00034.png","x":-29,"y":-95},
			{"res":"00035.png","x":-26,"y":-91},
			{"res":"00036.png","x":-29,"y":-68},
			{"res":"00037.png","x":-31,"y":-84},
			{"res":"00038.png","x":-31,"y":-113},
			{"res":"00039.png","x":-33,"y":-121}

		]
}},
"res":{
	"00032.png":{"x":0,"y":0,"w":51,"h":60},
	"00033.png":{"x":51,"y":0,"w":45,"h":98},
	"00034.png":{"x":96,"y":0,"w":33,"h":127},
	"00035.png":{"x":129,"y":0,"w":26,"h":127},
	"00036.png":{"x":155,"y":0,"w":33,"h":88},
	"00037.png":{"x":188,"y":0,"w":46,"h":73},
	"00038.png":{"x":234,"y":0,"w":50,"h":112},
	"00039.png":{"x":284,"y":0,"w":56,"h":123}

}}