{"mc":{
	"run6":{
		"frameRate":24,
		"frames":[
			{"res":"00820","x":-85,"y":-169},
			{"res":"00821","x":-83,"y":-168},
			{"res":"00822","x":-78,"y":-174},
			{"res":"00823","x":-87,"y":-169},
			{"res":"00824","x":-91,"y":-170},
			{"res":"00825","x":-78,"y":-174}

		]
}},
"res":{
	"00820":{"x":0,"y":0,"w":196,"h":202},
	"00821":{"x":196,"y":0,"w":194,"h":206},
	"00822":{"x":390,"y":0,"w":189,"h":215},
	"00823":{"x":579,"y":0,"w":198,"h":224},
	"00824":{"x":777,"y":0,"w":202,"h":205},
	"00825":{"x":979,"y":0,"w":189,"h":215}

}}