{"mc":{
	"stand9":{
		"frameRate":24,
		"frames":[
			{"res":"020002.png","x":-4,"y":-45},
			{"res":"020003.png","x":-4,"y":-45},
			{"res":"030000.png","x":-17,"y":-44},
			{"res":"030001.png","x":-17,"y":-44},
			{"res":"030002.png","x":-17,"y":-44},
			{"res":"030003.png","x":-17,"y":-44}

		]
}},
"res":{
	"020002.png":{"x":0,"y":0,"w":65,"h":19},
	"020003.png":{"x":65,"y":0,"w":66,"h":20},
	"030000.png":{"x":131,"y":0,"w":89,"h":46},
	"030001.png":{"x":220,"y":0,"w":90,"h":44},
	"030002.png":{"x":310,"y":0,"w":90,"h":45},
	"030003.png":{"x":400,"y":0,"w":90,"h":46}

}}