{"mc":{
	"stand":{
		"frameRate":24,
		"frames":[
			{"res":"010000","x":-83,"y":-82},
			{"res":"010001","x":-82,"y":-82},
			{"res":"010002","x":-80,"y":-82},
			{"res":"010003","x":-80,"y":-82},
			{"res":"010004","x":-80,"y":-82},
			{"res":"010005","x":-81,"y":-82}

		]
}},
"res":{
	"010000":{"x":0,"y":0,"w":159,"h":215},
	"010001":{"x":159,"y":0,"w":156,"h":215},
	"010002":{"x":315,"y":0,"w":155,"h":215},
	"010003":{"x":470,"y":0,"w":157,"h":215},
	"010004":{"x":627,"y":0,"w":155,"h":215},
	"010005":{"x":782,"y":0,"w":158,"h":215}

}}