{"mc":{
	"stand":{
		"frameRate":24,
		"frames":[
			{"res":"010000","x":-64,"y":-77},
			{"res":"010001","x":-63,"y":-77},
			{"res":"010002","x":-62,"y":-77},
			{"res":"010003","x":-62,"y":-77},
			{"res":"010004","x":-63,"y":-77},
			{"res":"010005","x":-64,"y":-77}

		]
}},
"res":{
	"010000":{"x":0,"y":0,"w":135,"h":212},
	"010001":{"x":135,"y":0,"w":133,"h":212},
	"010002":{"x":268,"y":0,"w":132,"h":212},
	"010003":{"x":400,"y":0,"w":131,"h":212},
	"010004":{"x":531,"y":0,"w":132,"h":212},
	"010005":{"x":663,"y":0,"w":134,"h":212}

}}