{"mc":{
	"run3":{
		"frameRate":24,
		"frames":[
			{"res":"00110","x":-16,"y":-53},
			{"res":"00111","x":-16,"y":-55},
			{"res":"00112","x":-16,"y":-56},
			{"res":"00113","x":-17,"y":-56},
			{"res":"00114","x":-17,"y":-55},
			{"res":"00115","x":-16,"y":-53}

		]
}},
"res":{
	"00110":{"x":0,"y":0,"w":121,"h":114},
	"00111":{"x":121,"y":0,"w":122,"h":116},
	"00112":{"x":243,"y":0,"w":124,"h":118},
	"00113":{"x":367,"y":0,"w":124,"h":118},
	"00114":{"x":491,"y":0,"w":123,"h":116},
	"00115":{"x":614,"y":0,"w":122,"h":115}

}}