{"mc":{
	"stand9":{
		"frameRate":24,
		"frames":[
			{"res":"020002.png","x":-23,"y":-53},
			{"res":"020003.png","x":-23,"y":-52},
			{"res":"030000.png","x":-36,"y":-53},
			{"res":"030001.png","x":-37,"y":-53},
			{"res":"030002.png","x":-36,"y":-53},
			{"res":"030003.png","x":-35,"y":-53}

		]
}},
"res":{
	"020002.png":{"x":0,"y":0,"w":118,"h":43},
	"020003.png":{"x":118,"y":0,"w":118,"h":42},
	"030000.png":{"x":236,"y":0,"w":148,"h":51},
	"030001.png":{"x":384,"y":0,"w":149,"h":49},
	"030002.png":{"x":533,"y":0,"w":148,"h":50},
	"030003.png":{"x":681,"y":0,"w":147,"h":51}

}}