{"mc":{
	"magic2":{
		"frameRate":24,
		"frames":[
			{"res":"10028.png","x":-108,"y":-215},
			{"res":"10029.png","x":-175,"y":-209},
			{"res":"10030.png","x":-170,"y":-227},
			{"res":"10031.png","x":-170,"y":-234},
			{"res":"10032.png","x":-112,"y":-241},
			{"res":"10033.png","x":-80,"y":-236},
			{"res":"10034.png","x":-92,"y":-227}

		]
}},
"res":{
	"10028.png":{"x":0,"y":0,"w":286,"h":232},
	"10029.png":{"x":286,"y":0,"w":303,"h":220},
	"10030.png":{"x":589,"y":0,"w":245,"h":259},
	"10031.png":{"x":834,"y":0,"w":222,"h":258},
	"10032.png":{"x":1056,"y":0,"w":168,"h":224},
	"10033.png":{"x":1224,"y":0,"w":139,"h":221},
	"10034.png":{"x":1363,"y":0,"w":246,"h":229}

}}