{"mc":{
	"hit":{
		"frameRate":24,
		"frames":[
			{"res":"010001","x":-44,"y":-114},
			{"res":"010002","x":-47,"y":-106},
			{"res":"010003","x":-50,"y":-106},
			{"res":"020001","x":-48,"y":-106},
			{"res":"020002","x":-45,"y":-108},
			{"res":"020003","x":-43,"y":-110},
			{"res":"030001","x":-54,"y":-117},
			{"res":"030002","x":-49,"y":-117},
			{"res":"030003","x":-54,"y":-115},
			{"res":"040001","x":-57,"y":-125},
			{"res":"040002","x":-61,"y":-123},
			{"res":"040003","x":-65,"y":-117},
			{"res":"050001","x":-49,"y":-127},
			{"res":"050002","x":-52,"y":-125},
			{"res":"050003","x":-59,"y":-118}

		]
}},
"res":{
	"010001":{"x":0,"y":0,"w":93,"h":127},
	"010002":{"x":93,"y":0,"w":99,"h":119},
	"010003":{"x":192,"y":0,"w":109,"h":119},
	"020001":{"x":301,"y":0,"w":112,"h":122},
	"020002":{"x":413,"y":0,"w":115,"h":124},
	"020003":{"x":528,"y":0,"w":116,"h":126},
	"030001":{"x":644,"y":0,"w":105,"h":130},
	"030002":{"x":749,"y":0,"w":102,"h":130},
	"030003":{"x":851,"y":0,"w":103,"h":128},
	"040001":{"x":954,"y":0,"w":100,"h":131},
	"040002":{"x":1054,"y":0,"w":105,"h":129},
	"040003":{"x":1159,"y":0,"w":107,"h":129},
	"050001":{"x":1266,"y":0,"w":93,"h":133},
	"050002":{"x":1359,"y":0,"w":99,"h":131},
	"050003":{"x":1458,"y":0,"w":109,"h":124}

}}