{"mc":{
	"magic3":{
		"frameRate":24,
		"frames":[
			{"res":"040000.png","x":-25,"y":-145},
			{"res":"040001.png","x":8,"y":-119},
			{"res":"040002.png","x":2,"y":-175},
			{"res":"040003.png","x":-32,"y":-181},
			{"res":"040004.png","x":-15,"y":-180},
			{"res":"040005.png","x":5,"y":-109},
			{"res":"040006.png","x":-13,"y":-127}

		]
}},
"res":{
	"040000.png":{"x":0,"y":0,"w":24,"h":95},
	"040001.png":{"x":24,"y":0,"w":32,"h":94},
	"040002.png":{"x":56,"y":0,"w":16,"h":99},
	"040003.png":{"x":72,"y":0,"w":40,"h":95},
	"040004.png":{"x":112,"y":0,"w":28,"h":100},
	"040005.png":{"x":140,"y":0,"w":64,"h":78},
	"040006.png":{"x":204,"y":0,"w":30,"h":96}

}}