{"mc":{
	"dead":{
		"frameRate":24,
		"frames":[
			{"res":"010001","x":-30,"y":-48},
			{"res":"010002","x":-33,"y":-103},
			{"res":"010003","x":-28,"y":-64},
			{"res":"010004","x":-33,"y":-42},
			{"res":"020001","x":-26,"y":-51},
			{"res":"020002","x":-30,"y":-102},
			{"res":"020003","x":-35,"y":-56},
			{"res":"020004","x":-37,"y":-46},
			{"res":"030001","x":-32,"y":-49},
			{"res":"030002","x":-16,"y":-96},
			{"res":"030003","x":-42,"y":-59},
			{"res":"030004","x":-45,"y":-50},
			{"res":"040001","x":-26,"y":-45},
			{"res":"040002","x":-28,"y":-88},
			{"res":"040003","x":-37,"y":-63},
			{"res":"040004","x":-42,"y":-46},
			{"res":"050001","x":-30,"y":-41},
			{"res":"050002","x":-35,"y":-85},
			{"res":"050003","x":-33,"y":-70},
			{"res":"050004","x":-32,"y":-51}

		]
}},
"res":{
	"010001":{"x":0,"y":0,"w":60,"h":58},
	"010002":{"x":60,"y":0,"w":68,"h":75},
	"010003":{"x":128,"y":0,"w":62,"h":57},
	"010004":{"x":190,"y":0,"w":65,"h":56},
	"020001":{"x":255,"y":0,"w":66,"h":57},
	"020002":{"x":321,"y":0,"w":76,"h":75},
	"020003":{"x":397,"y":0,"w":68,"h":52},
	"020004":{"x":465,"y":0,"w":65,"h":65},
	"030001":{"x":530,"y":0,"w":73,"h":52},
	"030002":{"x":603,"y":0,"w":66,"h":71},
	"030003":{"x":669,"y":0,"w":77,"h":53},
	"030004":{"x":746,"y":0,"w":80,"h":67},
	"040001":{"x":826,"y":0,"w":66,"h":50},
	"040002":{"x":892,"y":0,"w":75,"h":65},
	"040003":{"x":967,"y":0,"w":72,"h":52},
	"040004":{"x":1039,"y":0,"w":78,"h":59},
	"050001":{"x":1117,"y":0,"w":61,"h":45},
	"050002":{"x":1178,"y":0,"w":68,"h":63},
	"050003":{"x":1246,"y":0,"w":61,"h":60},
	"050004":{"x":1307,"y":0,"w":66,"h":66}

}}