{"mc":{
	"run9":{
		"frameRate":24,
		"frames":[
			{"res":"00008.png","x":-34,"y":-139},
			{"res":"00009.png","x":-61,"y":-75},
			{"res":"00010.png","x":-67,"y":-58},
			{"res":"00011.png","x":-66,"y":-56},
			{"res":"00012.png","x":-61,"y":-84},
			{"res":"00013.png","x":-28,"y":-148},
			{"res":"00014.png","x":-5,"y":-167},
			{"res":"00015.png","x":5,"y":-166}

		]
}},
"res":{
	"00008.png":{"x":0,"y":0,"w":108,"h":181},
	"00009.png":{"x":108,"y":0,"w":140,"h":63},
	"00010.png":{"x":248,"y":0,"w":141,"h":54},
	"00011.png":{"x":389,"y":0,"w":144,"h":55},
	"00012.png":{"x":533,"y":0,"w":153,"h":77},
	"00013.png":{"x":686,"y":0,"w":104,"h":188},
	"00014.png":{"x":790,"y":0,"w":63,"h":206},
	"00015.png":{"x":853,"y":0,"w":44,"h":208}

}}