{"mc":{
	"yuanbao":{
		"frameRate":24,
		"labels":[
			{"name":"yuanbao","frame":1,"end":6}
			
			],
		"events":[
			
			],
		"frames":[
			
			{
			"res":"001",
			"x":-71,
			"y":-57
			},
			{
			"res":"002",
			"x":-101,
			"y":-82
			},
			{
			"res":"003",
			"x":-104,
			"y":-85
			},
			{
			"res":"004",
			"x":-104,
			"y":-85
			},
			{
			"res":"005",
			"x":-104,
			"y":-85
			},
			{
			"res":"006",
			"x":-103,
			"y":-85
			}
			]
}},
	"res":{
		"001":{"x":843,"y":0,"w":144,"h":123},
		"006":{"x":422,"y":0,"w":208,"h":178},
		"003":{"x":211,"y":0,"w":209,"h":178},
		"005":{"x":0,"y":0,"w":209,"h":178},
		"004":{"x":632,"y":0,"w":209,"h":177},
		"002":{"x":632,"y":179,"w":204,"h":173}
	}}