{"mc":{
	"run3":{
		"frameRate":24,
		"frames":[
			{"res":"040000.png","x":-8,"y":-70},
			{"res":"040001.png","x":-25,"y":-45},
			{"res":"040002.png","x":-29,"y":-53},
			{"res":"040003.png","x":-26,"y":-50},
			{"res":"040004.png","x":-17,"y":-38},
			{"res":"040005.png","x":0,"y":-76},
			{"res":"040006.png","x":8,"y":-102},
			{"res":"040007.png","x":7,"y":-107}

		]
}},
"res":{
	"040000.png":{"x":0,"y":0,"w":53,"h":44},
	"040001.png":{"x":53,"y":0,"w":70,"h":38},
	"040002.png":{"x":123,"y":0,"w":63,"h":56},
	"040003.png":{"x":186,"y":0,"w":59,"h":57},
	"040004.png":{"x":245,"y":0,"w":64,"h":33},
	"040005.png":{"x":309,"y":0,"w":47,"h":49},
	"040006.png":{"x":356,"y":0,"w":31,"h":72},
	"040007.png":{"x":387,"y":0,"w":27,"h":79}

}}