{"mc":{
	"run9":{
		"frameRate":24,
		"frames":[
			{"res":"020000.png","x":14,"y":-114},
			{"res":"020001.png","x":-3,"y":-64},
			{"res":"020002.png","x":-8,"y":-44},
			{"res":"020003.png","x":-7,"y":-41},
			{"res":"020004.png","x":4,"y":-70},
			{"res":"020005.png","x":19,"y":-122},
			{"res":"020006.png","x":25,"y":-134},
			{"res":"020007.png","x":22,"y":-131}

		]
}},
"res":{
	"020000.png":{"x":0,"y":0,"w":38,"h":83},
	"020001.png":{"x":38,"y":0,"w":59,"h":35},
	"020002.png":{"x":97,"y":0,"w":61,"h":15},
	"020003.png":{"x":158,"y":0,"w":64,"h":13},
	"020004.png":{"x":222,"y":0,"w":63,"h":41},
	"020005.png":{"x":285,"y":0,"w":36,"h":84},
	"020006.png":{"x":321,"y":0,"w":17,"h":86},
	"020007.png":{"x":338,"y":0,"w":12,"h":85}

}}