{"mc":{
	"run9":{
		"frameRate":24,
		"frames":[
			{"res":"020000.png","x":-68,"y":-99},
			{"res":"020001.png","x":-60,"y":-100},
			{"res":"020002.png","x":-54,"y":-101},
			{"res":"020003.png","x":-56,"y":-100},
			{"res":"020004.png","x":-57,"y":-99},
			{"res":"020005.png","x":-56,"y":-100},
			{"res":"020006.png","x":-59,"y":-101},
			{"res":"020007.png","x":-73,"y":-100}

		]
}},
"res":{
	"020000.png":{"x":0,"y":0,"w":105,"h":109},
	"020001.png":{"x":105,"y":0,"w":88,"h":107},
	"020002.png":{"x":193,"y":0,"w":77,"h":106},
	"020003.png":{"x":270,"y":0,"w":82,"h":100},
	"020004.png":{"x":352,"y":0,"w":79,"h":103},
	"020005.png":{"x":431,"y":0,"w":85,"h":109},
	"020006.png":{"x":516,"y":0,"w":91,"h":108},
	"020007.png":{"x":607,"y":0,"w":104,"h":110}

}}