{"mc":{
	"run2":{
		"frameRate":24,
		"frames":[
			{"res":"050000.png","x":-40,"y":-83},
			{"res":"050001.png","x":-46,"y":-84},
			{"res":"050002.png","x":-43,"y":-84},
			{"res":"050003.png","x":-31,"y":-83},
			{"res":"050004.png","x":-25,"y":-83},
			{"res":"050005.png","x":-26,"y":-83},
			{"res":"050006.png","x":-27,"y":-84},
			{"res":"050007.png","x":-34,"y":-83}

		]
}},
"res":{
	"050000.png":{"x":0,"y":0,"w":66,"h":90},
	"050001.png":{"x":66,"y":0,"w":72,"h":90},
	"050002.png":{"x":138,"y":0,"w":73,"h":94},
	"050003.png":{"x":211,"y":0,"w":69,"h":96},
	"050004.png":{"x":280,"y":0,"w":69,"h":90},
	"050005.png":{"x":349,"y":0,"w":75,"h":89},
	"050006.png":{"x":424,"y":0,"w":76,"h":94},
	"050007.png":{"x":500,"y":0,"w":71,"h":95}

}}