{"mc":{
	"run3":{
		"frameRate":24,
		"frames":[
			{"res":"040000.png","x":-104,"y":-81},
			{"res":"040001.png","x":-104,"y":-80},
			{"res":"040002.png","x":-104,"y":-79},
			{"res":"040003.png","x":-104,"y":-73},
			{"res":"040004.png","x":-104,"y":-72},
			{"res":"040005.png","x":-104,"y":-71},
			{"res":"040006.png","x":-104,"y":-80},
			{"res":"040007.png","x":-104,"y":-82}

		]
}},
"res":{
	"040000.png":{"x":0,"y":0,"w":110,"h":96},
	"040001.png":{"x":110,"y":0,"w":110,"h":96},
	"040002.png":{"x":220,"y":0,"w":110,"h":96},
	"040003.png":{"x":330,"y":0,"w":103,"h":88},
	"040004.png":{"x":433,"y":0,"w":103,"h":88},
	"040005.png":{"x":536,"y":0,"w":103,"h":88},
	"040006.png":{"x":639,"y":0,"w":110,"h":96},
	"040007.png":{"x":749,"y":0,"w":110,"h":96}

}}