{"mc":{
	"run6":{
		"frameRate":24,
		"frames":[
			{"res":"030000.PNG","x":-39,"y":-156},
			{"res":"030001.PNG","x":-49,"y":-151},
			{"res":"030002.PNG","x":-57,"y":-151},
			{"res":"030003.PNG","x":-62,"y":-154},
			{"res":"030004.PNG","x":-57,"y":-151},
			{"res":"030005.PNG","x":-46,"y":-154}

		]
}},
"res":{
	"030000.PNG":{"x":0,"y":0,"w":151,"h":171},
	"030001.PNG":{"x":151,"y":0,"w":149,"h":167},
	"030002.PNG":{"x":300,"y":0,"w":148,"h":170},
	"030003.PNG":{"x":448,"y":0,"w":145,"h":178},
	"030004.PNG":{"x":593,"y":0,"w":146,"h":179},
	"030005.PNG":{"x":739,"y":0,"w":147,"h":174}

}}