{"mc":{
	"magic8":{
		"frameRate":24,
		"frames":[
			{"res":"010000.png","x":-55,"y":-89},
			{"res":"010001.png","x":-54,"y":-97},
			{"res":"010002.png","x":-45,"y":-102},
			{"res":"010003.png","x":-37,"y":-98},
			{"res":"010004.png","x":-42,"y":-100},
			{"res":"010005.png","x":-46,"y":-92},
			{"res":"010006.png","x":-45,"y":-89}

		]
}},
"res":{
	"010000.png":{"x":0,"y":0,"w":91,"h":122},
	"010001.png":{"x":91,"y":0,"w":93,"h":123},
	"010002.png":{"x":184,"y":0,"w":88,"h":130},
	"010003.png":{"x":272,"y":0,"w":100,"h":138},
	"010004.png":{"x":372,"y":0,"w":124,"h":147},
	"010005.png":{"x":496,"y":0,"w":132,"h":125},
	"010006.png":{"x":628,"y":0,"w":124,"h":121}

}}