{"mc":{
	"stand":{
		"frameRate":24,
		"frames":[
			{"res":"00000","x":-80,"y":-78},
			{"res":"00001","x":-80,"y":-78},
			{"res":"00002","x":-82,"y":-78},
			{"res":"00003","x":-85,"y":-78},
			{"res":"00004","x":-86,"y":-78},
			{"res":"00005","x":-84,"y":-78}

		]
}},
"res":{
	"00000":{"x":0,"y":0,"w":134,"h":209},
	"00001":{"x":134,"y":0,"w":134,"h":209},
	"00002":{"x":268,"y":0,"w":136,"h":209},
	"00003":{"x":404,"y":0,"w":138,"h":209},
	"00004":{"x":542,"y":0,"w":143,"h":209},
	"00005":{"x":685,"y":0,"w":140,"h":209}

}}