{"mc":{
	"run2":{
		"frameRate":24,
		"frames":[
			{"res":"00120","x":-57,"y":-156},
			{"res":"00121","x":-48,"y":-154},
			{"res":"00122","x":-53,"y":-158},
			{"res":"00123","x":-63,"y":-156},
			{"res":"00124","x":-74,"y":-154},
			{"res":"00125","x":-59,"y":-157}

		]
}},
"res":{
	"00120":{"x":0,"y":0,"w":223,"h":255},
	"00121":{"x":223,"y":0,"w":213,"h":251},
	"00122":{"x":436,"y":0,"w":221,"h":240},
	"00123":{"x":657,"y":0,"w":226,"h":230},
	"00124":{"x":883,"y":0,"w":233,"h":227},
	"00125":{"x":1116,"y":0,"w":225,"h":247}

}}