{"mc":{
	"run2":{
		"frameRate":24,
		"frames":[
			{"res":"00120","x":-115,"y":-177},
			{"res":"00121","x":-112,"y":-184},
			{"res":"00122","x":-104,"y":-177},
			{"res":"00123","x":-103,"y":-163},
			{"res":"00124","x":-106,"y":-175},
			{"res":"00125","x":-119,"y":-168}

		]
}},
"res":{
	"00120":{"x":0,"y":0,"w":320,"h":233},
	"00121":{"x":320,"y":0,"w":318,"h":229},
	"00122":{"x":638,"y":0,"w":318,"h":217},
	"00123":{"x":956,"y":0,"w":331,"h":220},
	"00124":{"x":1287,"y":0,"w":337,"h":220},
	"00125":{"x":1624,"y":0,"w":341,"h":208}

}}