{"mc":{
	"magic2":{
		"frameRate":24,
		"frames":[
			{"res":"050000.png","x":-34,"y":-136},
			{"res":"050001.png","x":-15,"y":-80},
			{"res":"050002.png","x":-2,"y":-145},
			{"res":"050003.png","x":-7,"y":-163},
			{"res":"050004.png","x":-1,"y":-156},
			{"res":"050005.png","x":-16,"y":-62},
			{"res":"050006.png","x":-30,"y":-104}

		]
}},
"res":{
	"050000.png":{"x":0,"y":0,"w":46,"h":79},
	"050001.png":{"x":46,"y":0,"w":31,"h":56},
	"050002.png":{"x":77,"y":0,"w":8,"h":75},
	"050003.png":{"x":85,"y":0,"w":14,"h":83},
	"050004.png":{"x":99,"y":0,"w":9,"h":82},
	"050005.png":{"x":108,"y":0,"w":38,"h":33},
	"050006.png":{"x":146,"y":0,"w":11,"h":67}

}}